Metadata-Version: 2.1
Name: ocr-jm
Version: 0.0.9
Summary: Modification on top of OpenMMLab Text Detection, OCR, and NLP Toolbox
Home-page: https://github.com/NaJaeMin92
Maintainer: MMOCR Authors
Maintainer-email: fixbi46@gmail.com
License: Apache License 2.0
Keywords: Text Detection,OCR,KIE,NLP
Platform: UNKNOWN
Classifier: Development Status :: 4 - Beta
Classifier: License :: OSI Approved :: Apache Software License
Classifier: Operating System :: OS Independent
Classifier: Programming Language :: Python :: 3
Classifier: Programming Language :: Python :: 3.6
Classifier: Programming Language :: Python :: 3.7
Classifier: Programming Language :: Python :: 3.8
Classifier: Programming Language :: Python :: 3.9
License-File: LICENSE
Requires-Dist: imgaug
Requires-Dist: lmdb
Requires-Dist: matplotlib
Requires-Dist: numpy
Requires-Dist: opencv-python !=4.5.5.*,>=4.2.0.32
Requires-Dist: pyclipper
Requires-Dist: pycocotools
Requires-Dist: rapidfuzz >=2.0.0
Requires-Dist: scikit-image
Provides-Extra: all
Requires-Dist: numpy ; extra == 'all'
Requires-Dist: pyclipper ; extra == 'all'
Requires-Dist: boto3 ; extra == 'all'
Requires-Dist: imgaug ; extra == 'all'
Requires-Dist: lmdb ; extra == 'all'
Requires-Dist: matplotlib ; extra == 'all'
Requires-Dist: opencv-python !=4.5.5.*,>=4.2.0.32 ; extra == 'all'
Requires-Dist: pycocotools ; extra == 'all'
Requires-Dist: rapidfuzz >=2.0.0 ; extra == 'all'
Requires-Dist: scikit-image ; extra == 'all'
Requires-Dist: asynctest ; extra == 'all'
Requires-Dist: codecov ; extra == 'all'
Requires-Dist: flake8 ; extra == 'all'
Requires-Dist: interrogate ; extra == 'all'
Requires-Dist: isort ; extra == 'all'
Requires-Dist: kwarray ; extra == 'all'
Requires-Dist: lanms-neo ==1.0.2 ; extra == 'all'
Requires-Dist: parameterized ; extra == 'all'
Requires-Dist: pytest ; extra == 'all'
Requires-Dist: pytest-cov ; extra == 'all'
Requires-Dist: pytest-runner ; extra == 'all'
Requires-Dist: ubelt ; extra == 'all'
Requires-Dist: xdoctest >=0.10.0 ; extra == 'all'
Requires-Dist: yapf ; extra == 'all'
Provides-Extra: build
Requires-Dist: numpy ; extra == 'build'
Requires-Dist: pyclipper ; extra == 'build'
Provides-Extra: mim
Requires-Dist: mmcv <2.2.0,>=2.0.0rc4 ; extra == 'mim'
Requires-Dist: mmdet <3.4.0,>=3.0.0rc5 ; extra == 'mim'
Requires-Dist: mmengine <1.1.0,>=0.7.0 ; extra == 'mim'
Provides-Extra: optional
Requires-Dist: boto3 ; extra == 'optional'
Provides-Extra: tests
Requires-Dist: asynctest ; extra == 'tests'
Requires-Dist: codecov ; extra == 'tests'
Requires-Dist: flake8 ; extra == 'tests'
Requires-Dist: interrogate ; extra == 'tests'
Requires-Dist: isort ; extra == 'tests'
Requires-Dist: kwarray ; extra == 'tests'
Requires-Dist: lanms-neo ==1.0.2 ; extra == 'tests'
Requires-Dist: parameterized ; extra == 'tests'
Requires-Dist: pytest ; extra == 'tests'
Requires-Dist: pytest-cov ; extra == 'tests'
Requires-Dist: pytest-runner ; extra == 'tests'
Requires-Dist: ubelt ; extra == 'tests'
Requires-Dist: xdoctest >=0.10.0 ; extra == 'tests'
Requires-Dist: yapf ; extra == 'tests'
